serverpilot/__init__.py
serverpilot/serverpilot.py
rwsp-1.0.1.dist-info/LICENSE
rwsp-1.0.1.dist-info/METADATA
rwsp-1.0.1.dist-info/WHEEL
rwsp-1.0.1.dist-info/top_level.txt
rwsp-1.0.1.dist-info/RECORD
