Metadata-Version: 2.1
Name: rwsp
Version: 1.0.1
Summary: A Python package to interact with ServerPilot API.
Home-page: https://github.com/rehmatworks/serverpilot-python
Author: Rehmat
Author-email: contact@rehmat.works
License: MIT
Platform: UNKNOWN
Requires-Dist: requests
